[
  {
    "id": 1,
    "name": "one",
     "size": 390
  },
  {
    "id": 2,
    "name": "persons",
    "parent": 1,
     "size": 3090
  },
  {
    "id": 4,
    "name": "Persone1",
    "parent": 2,
    "size": 3938
  },
  {
    "id": 5,
    "name": "Persone2",
    "parent": 2,
    "size": 3812
  },
  {
    "id": 6,
    "name": "Persone3",
    "parent": 2,
    "size": 6714
  },
  {
    "id": 7,
    "name": "Persone4",
    "parent": 2,
    "size": 3938
  },
  {
    "id": 8,
    "name": "Persone5",
    "parent": 2,
    "size": 3812
  },
  {
    "id": 9,
    "name": "Persone6",
    "parent": 2,
    "size": 6714
  },
   {
    "id": 10,
    "name": "Persone1_2",
    "parent": 1,
    "size": 3938
  },
  {
    "id": 11,
    "name": "Persone2_2",
    "parent": 1,
    "size": 3812
  },
  {
    "id": 12,
    "name": "Persone3_2",
    "parent": 1,
    "size": 6714
  },
  {
    "id": 13,
    "name": "Persone4_2",
    "parent": 1,
    "size": 3938
  },
  {
    "id": 14,
    "name": "Persone5_2",
    "parent": 1,
    "size": 3812
  },
  {
    "id": 15,
    "name": "Persone6_2",
    "parent": 1,
    "size": 6714
  }
  {
    "id": 16,
    "name": "Project7",
    "parent": 10,
    "size": 743
  },
  {
    "id": 17,
    "name": "Projecteight",
    "parent": 11
  },
  {
    "id": 18,
    "name": "Projectnine",
    "parent": 12,
    "size": 3534
  },
  {
    "id": 19,
    "name": "Projectten",
    "parent": 13,
    "size": 5731
  },
  {
    "id": 20,
    "name": "Projecteleven",
    "parent": 14,
    "size": 7840
  },
  {
    "id": 21,
    "name": "Projecttwelve",
    "parent": 15,
    "size": 5914
  },
  {
    "id": 22,
    "name": "Projecttherteen",
    "parent": 12,
    "size": 3416
  },
  {
    "id": 23,
    "name": "Projectfourteen",
    "parent": 11
  },
  {
    "id": 24,
    "name": "Projectfifteen",
    "parent": 10,
    "size": 7074
  },
  {
    "id": 25,
    "name": "Projectsixteen",
    "parent": 10
  },
  {
    "id": 26,
    "name": "Projectseventeen",
    "parent": 14,
    "size": 17010
  },
  {
    "id": 27,
    "name": "Projecteighteen",
    "parent": 15,
    "size": 5842
  },
  {
    "id": 28,
    "name": "Projectnineteen",
    "parent": 14
  },
  {
    "id": 29,
    "name": "Projecttwenty",
    "parent": 13,
    "size": 1983
  }]
