[{"source":4,"target":114},
{"source":4,"target":115},
{"source":4,"target":116},
{"source":5,"target":117},
{"source":6,"target":118},
{"source":7,"target":119},
{"source":8,"target":120},
{"source":9,"target":121},
{"source":10,"target":122},
{"source":11,"target":123},
{"source":12,"target":124},
{"source":13,"target":125},
{"source":14,"target":126},
{"source":15,"target":127},
{"source":16,"target":128},
{"source":17,"target":129},
{"source":17,"target":130},
{"source":18,"target":131},
{"source":19,"target":132},
{"source":20,"target":133},
{"source":20,"target":134},
{"source":21,"target":135},
{"source":22,"target":136},
{"source":22,"target":137},
{"source":23,"target":138},
{"source":24,"target":139},
{"source":25,"target":140},
{"source":26,"target":141},
{"source":26,"target":142},
{"source":27,"target":143},
{"source":28,"target":144},
{"source":29,"target":145},
{"source":30,"target":146},
{"source":31,"target":147},
{"source":32,"target":148},
{"source":33,"target":149},
{"source":33,"target":150},
{"source":34,"target":151},
{"source":35,"target":152},
{"source":36,"target":153},
{"source":37,"target":154},
{"source":38,"target":155},
{"source":39,"target":156},
{"source":40,"target":157},
{"source":41,"target":158},
{"source":42,"target":159},
{"source":43,"target":160},
{"source":43,"target":161},
{"source":44,"target":162},
{"source":45,"target":163},
{"source":46,"target":164},
{"source":47,"target":165},
{"source":48,"target":166},
{"source":49,"target":167},
{"source":50,"target":168},
{"source":51,"target":169},
{"source":52,"target":170},
{"source":53,"target":171},
{"source":54,"target":172},
{"source":55,"target":173},
{"source":56,"target":174},
{"source":57,"target":175},
{"source":58,"target":176}]
